[
  {
    "id": 2,
    "title": "Inception",
    "director": "Christopher Nolan",
    "year": 2010
  },
  {
    "id": 3,
    "title": "El Padrino",
    "director": "Francis Ford Coppola",
    "year": 1972
  },
  {
    "id": 4,
    "title": "Avengers: Endgame",
    "director": "Anthony y Joe Russo",
    "year": 2019
  },
  {
    "id": 5,
    "title": "Parasite",
    "director": "Bong Joon-ho",
    "year": 2019
  },
  {
    "id": 6,
    "title": "Forrest Gump",
    "director": "Robert Zemeckis",
    "year": 1994
  },
  {
    "title": "Interstellar",
    "director": "Christopher Nolan",
    "year": 2014,
    "id": 7
  }
]